winpwn/__init__.py
winpwn/context.py
winpwn/dbg.py
winpwn/misc.py
winpwn/var.py
winpwn/win.py
winpwn/winpwn.py
bypwn-0.0.1.dist-info/METADATA
bypwn-0.0.1.dist-info/WHEEL
bypwn-0.0.1.dist-info/top_level.txt
bypwn-0.0.1.dist-info/RECORD
